[
  {
    "title": "مولودية الجزائر يفتتح الموسم بفوز مهم على شبيبة القبائل",
    "date": "2025-08-16T19:30:00Z",
    "image": "https://example.com/mca.jpg",
    "link": "https://example.com/article1",
    "source": "الهداف",
    "summary": "مولودية الجزائر يبدأ الموسم بانتصار مهم...",
    "content": "في مباراة مثيرة تمكن نادي مولودية الجزائر من تحقيق فوز مهم على شبيبة القبائل..."
  },
  {
    "title": "شباب بلوزداد يعلن عن صفقة مهاجم جديد",
    "date": "2025-08-15T15:00:00Z",
    "image": "https://example.com/crb.jpg",
    "link": "https://example.com/article2",
    "source": "الشروق",
    "summary": "شباب بلوزداد يبرم صفقة جديدة...",
    "content": "أعلن نادي شباب بلوزداد عن تعاقده مع مهاجم جديد قادم من الدوري التونسي..."
  },
  {
    "title": "الرابطة تكشف برنامج الجولة الثانية",
    "date": "2025-08-14T10:00:00Z",
    "image": "https://example.com/lnfp.jpg",
    "link": "https://example.com/article3",
    "source": "الفاف",
    "summary": "الرابطة المحترفة تكشف تفاصيل الجولة القادمة...",
    "content": "أصدرت رابطة كرة القدم المحترفة برنامج الجولة الثانية من الدوري الجزائري للمحترفين..."
  }
]
